{
  "annotations": {
    "list": [
      {
        "builtIn": 1,
        "datasource": {
          "type": "grafana",
          "uid": "-- Grafana --"
        },
        "enable": true,
        "hide": true,
        "iconColor": "rgba(0, 211, 255, 1)",
        "name": "Annotations & Alerts",
        "type": "dashboard"
      }
    ]
  },
  "editable": true,
  "fiscalYearStartMonth": 0,
  "graphTooltip": 1,
  "id": null,
  "links": [],
  "liveNow": false,
  "panels": [
    {
      "collapsed": false,
      "gridPos": {
        "h": 1,
        "w": 24,
        "x": 0,
        "y": 0
      },
      "id": 100,
      "panels": [],
      "title": "System Status & Health",
      "type": "row"
    },
    {
      "datasource": {
        "type": "prometheus",
        "uid": "openbrain-prometheus"
      },
      "fieldConfig": {
        "defaults": {
          "color": {
            "mode": "thresholds"
          },
          "mappings": [
            {
              "options": {
                "0": {
                  "color": "green",
                  "index": 0,
                  "text": "HEALTHY"
                },
                "1": {
                  "color": "orange",
                  "index": 1,
                  "text": "WATCH"
                },
                "2": {
                  "color": "red",
                  "index": 2,
                  "text": "ELEVATED"
                }
              },
              "type": "value"
            }
          ],
          "thresholds": {
            "mode": "absolute",
            "steps": [
              {
                "color": "green",
                "value": null
              },
              {
                "color": "orange",
                "value": 1
              },
              {
                "color": "red",
                "value": 2
              }
            ]
          }
        },
        "overrides": []
      },
      "gridPos": {
        "h": 4,
        "w": 6,
        "x": 0,
        "y": 1
      },
      "id": 1,
      "options": {
        "colorMode": "background",
        "graphMode": "none",
        "justifyMode": "center",
        "orientation": "auto",
        "reduceOptions": {
          "calcs": [
            "lastNotNull"
          ],
          "fields": "",
          "values": false
        },
        "textMode": "value"
      },
      "targets": [
        {
          "expr": "operational_health_status",
          "refId": "A"
        }
      ],
      "title": "Operational Health Status",
      "type": "stat"
    },
    {
      "datasource": {
        "type": "prometheus",
        "uid": "openbrain-prometheus"
      },
      "fieldConfig": {
        "defaults": {
          "color": {
            "mode": "palette-classic"
          },
          "unit": "short"
        },
        "overrides": []
      },
      "gridPos": {
        "h": 4,
        "w": 6,
        "x": 6,
        "y": 1
      },
      "id": 11,
      "options": {
        "colorMode": "value",
        "graphMode": "area",
        "justifyMode": "center",
        "orientation": "auto",
        "reduceOptions": {
          "calcs": [
            "lastNotNull"
          ],
          "fields": "",
          "values": false
        },
        "textMode": "auto"
      },
      "targets": [
        {
          "expr": "active_memories_total",
          "refId": "A"
        }
      ],
      "title": "Total Active Memories",
      "type": "stat"
    },
    {
      "datasource": {
        "type": "prometheus",
        "uid": "openbrain-prometheus"
      },
      "fieldConfig": {
        "defaults": {
          "color": {
            "mode": "thresholds"
          },
          "thresholds": {
            "mode": "absolute",
            "steps": [
              {
                "color": "green",
                "value": null
              },
              {
                "color": "red",
                "value": 1
              }
            ]
          },
          "unit": "short"
        }
      },
      "gridPos": {
        "h": 4,
        "w": 6,
        "x": 12,
        "y": 1
      },
      "id": 12,
      "options": {
        "colorMode": "value",
        "graphMode": "area",
        "justifyMode": "center",
        "orientation": "auto",
        "reduceOptions": {
          "calcs": [
            "lastNotNull"
          ],
          "fields": "",
          "values": false
        },
        "textMode": "auto"
      },
      "targets": [
        {
          "expr": "sum(increase(http_requests_total_500[5m])) or vector(0)",
          "refId": "A"
        }
      ],
      "title": "Errors (Last 5m)",
      "type": "stat"
    },
    {
      "datasource": {
        "type": "prometheus",
        "uid": "openbrain-prometheus"
      },
      "fieldConfig": {
        "defaults": {
          "color": {
            "mode": "palette-classic"
          },
          "unit": "s"
        }
      },
      "gridPos": {
        "h": 4,
        "w": 6,
        "x": 18,
        "y": 1
      },
      "id": 13,
      "options": {
        "colorMode": "value",
        "graphMode": "area",
        "justifyMode": "center",
        "orientation": "auto",
        "reduceOptions": {
          "calcs": [
            "mean"
          ],
          "fields": "",
          "values": false
        },
        "textMode": "auto"
      },
      "targets": [
        {
          "expr": "rate(http_request_duration_seconds_sum[5m]) / rate(http_request_duration_seconds_count[5m])",
          "refId": "A"
        }
      ],
      "title": "Avg Latency (5m)",
      "type": "stat"
    },
    {
      "collapsed": false,
      "gridPos": {
        "h": 1,
        "w": 24,
        "x": 0,
        "y": 5
      },
      "id": 101,
      "panels": [],
      "title": "Traffic & Performance",
      "type": "row"
    },
    {
      "datasource": {
        "type": "prometheus",
        "uid": "openbrain-prometheus"
      },
      "fieldConfig": {
        "defaults": {
          "color": {
            "mode": "palette-classic"
          },
          "custom": {
            "drawStyle": "line",
            "fillOpacity": 10,
            "lineWidth": 2
          },
          "unit": "reqps"
        }
      },
      "gridPos": {
        "h": 8,
        "w": 12,
        "x": 0,
        "y": 6
      },
      "id": 21,
      "options": {
        "legend": {
          "calcs": ["mean", "max"],
          "displayMode": "table",
          "placement": "bottom"
        }
      },
      "targets": [
        {
          "expr": "sum by (status) (rate(http_requests_total_200[5m]))",
          "legendFormat": "2xx Success",
          "refId": "A"
        },
        {
          "expr": "sum by (status) (rate(http_requests_total_401[5m])) + sum by (status) (rate(http_requests_total_403[5m]))",
          "legendFormat": "4xx Auth/Forbidden",
          "refId": "B"
        },
        {
          "expr": "sum by (status) (rate(http_requests_total_404[5m]))",
          "legendFormat": "404 Not Found",
          "refId": "C"
        },
        {
          "expr": "sum by (status) (rate(http_requests_total_500[5m])) + sum by (status) (rate(http_requests_total_502[5m])) + sum by (status) (rate(http_requests_total_503[5m]))",
          "legendFormat": "5xx Errors",
          "refId": "D"
        }
      ],
      "title": "Request Rate by Status",
      "type": "timeseries"
    },
    {
      "datasource": {
        "type": "prometheus",
        "uid": "openbrain-prometheus"
      },
      "fieldConfig": {
        "defaults": {
          "color": {
            "mode": "palette-classic"
          },
          "unit": "s"
        }
      },
      "gridPos": {
        "h": 8,
        "w": 12,
        "x": 12,
        "y": 6
      },
      "id": 22,
      "options": {
        "legend": {
          "calcs": ["mean", "lastNotNull"],
          "displayMode": "table",
          "placement": "bottom"
        }
      },
      "targets": [
        {
          "expr": "histogram_quantile(0.99, sum by (le) (rate(http_request_duration_seconds_bucket[5m])))",
          "legendFormat": "p99",
          "refId": "A"
        },
        {
          "expr": "histogram_quantile(0.95, sum by (le) (rate(http_request_duration_seconds_bucket[5m])))",
          "legendFormat": "p95",
          "refId": "B"
        },
        {
          "expr": "histogram_quantile(0.50, sum by (le) (rate(http_request_duration_seconds_bucket[5m])))",
          "legendFormat": "p50 (median)",
          "refId": "C"
        }
      ],
      "title": "Request Latency Quantiles",
      "type": "timeseries"
    },
    {
      "collapsed": false,
      "gridPos": {
        "h": 1,
        "w": 24,
        "x": 0,
        "y": 14
      },
      "id": 102,
      "panels": [],
      "title": "Memory Lifecycle & Content",
      "type": "row"
    },
    {
      "datasource": {
        "type": "prometheus",
        "uid": "openbrain-prometheus"
      },
      "gridPos": {
        "h": 8,
        "w": 12,
        "x": 0,
        "y": 15
      },
      "id": 31,
      "options": {
        "legend": {
          "displayMode": "list",
          "placement": "bottom"
        }
      },
      "targets": [
        {
          "expr": "rate(memories_created_total[5m])",
          "legendFormat": "Created",
          "refId": "A"
        },
        {
          "expr": "rate(memories_updated_total[5m])",
          "legendFormat": "Updated (In-place)",
          "refId": "B"
        },
        {
          "expr": "rate(memories_versioned_total[5m])",
          "legendFormat": "Versioned (Corporate)",
          "refId": "C"
        },
        {
          "expr": "rate(memories_deleted_total[5m])",
          "legendFormat": "Deleted",
          "refId": "D"
        }
      ],
      "title": "Write Activity (Rate/s)",
      "type": "timeseries"
    },
    {
      "datasource": {
        "type": "prometheus",
        "uid": "openbrain-prometheus"
      },
      "gridPos": {
        "h": 8,
        "w": 12,
        "x": 12,
        "y": 15
      },
      "id": 32,
      "options": {
        "legend": {
          "displayMode": "list",
          "placement": "bottom"
        }
      },
      "targets": [
        {
          "expr": "active_memories_corporate_total",
          "legendFormat": "Corporate",
          "refId": "A"
        },
        {
          "expr": "active_memories_build_total",
          "legendFormat": "Build",
          "refId": "B"
        },
        {
          "expr": "active_memories_personal_total",
          "legendFormat": "Personal",
          "refId": "C"
        }
      ],
      "title": "Active Memories Distribution",
      "type": "timeseries"
    },
    {
      "collapsed": false,
      "gridPos": {
        "h": 1,
        "w": 24,
        "x": 0,
        "y": 23
      },
      "id": 103,
      "panels": [],
      "title": "Maintenance & Governance",
      "type": "row"
    },
    {
      "datasource": {
        "type": "prometheus",
        "uid": "openbrain-prometheus"
      },
      "gridPos": {
        "h": 8,
        "w": 12,
        "x": 0,
        "y": 24
      },
      "id": 41,
      "options": {
        "legend": {
          "displayMode": "list",
          "placement": "bottom"
        }
      },
      "targets": [
        {
          "expr": "policy_skip_per_maintain_run_ratio",
          "legendFormat": "Policy Skip Ratio",
          "refId": "A"
        },
        {
          "expr": "duplicate_candidates_per_maintain_run_ratio",
          "legendFormat": "Duplicate Candidate Ratio",
          "refId": "B"
        }
      ],
      "title": "Maintenance Ratios",
      "type": "timeseries"
    },
    {
      "datasource": {
        "type": "prometheus",
        "uid": "openbrain-prometheus"
      },
      "gridPos": {
        "h": 8,
        "w": 12,
        "x": 12,
        "y": 24
      },
      "id": 42,
      "options": {
        "legend": {
          "displayMode": "list",
          "placement": "bottom"
        }
      },
      "targets": [
        {
          "expr": "policy_skip_delete_total",
          "legendFormat": "Delete Blocked",
          "refId": "A"
        },
        {
          "expr": "policy_skip_dedup_total",
          "legendFormat": "Dedup Blocked",
          "refId": "B"
        },
        {
          "expr": "policy_skip_owner_normalization_total",
          "legendFormat": "Normalization Blocked",
          "refId": "C"
        }
      ],
      "title": "Policy Skip Reasons (Cumulative)",
      "type": "timeseries"
    }
  ],
  "refresh": "30s",
  "schemaVersion": 39,
  "style": "dark",
  "tags": [
    "openbrain"
  ],
  "templating": {
    "list": []
  },
  "time": {
    "from": "now-6h",
    "to": "now"
  },
  "timepicker": {},
  "timezone": "",
  "title": "OpenBrain Professional Overview",
  "uid": "openbrain-overview",
  "version": 3,
  "weekStart": ""
}
